{
  "minecraft": "Minecraft",
  "mcp": "Minecraft Coder Pack",
  "FML": "Forge Mod Loader",
  "forge": "Minecraft Forge",
  "incorporeal_core": "Incoremod-poreal",
  "jecharacters": "Just Enough Characters",
  "persistency": "Persistency",
  "smoothfontcore": "Smooth Font Core",
  "mixinbooter": "MixinBooter",
  "biometweakercore": "BiomeTweakerCore",
  "foamfixcore": "FoamFixCore",
  "opencomputers|core": "OpenComputers (Core)",
  "rpintegration": "RandomPatches Integration",
  "botania_tweaks_core": "Botania Tweaks Core",
  "randompatches": "RandomPatches",
  "smoothfont": "Smooth Font",
  "tweakersconstruct": "Tweakers Construct",
  "customskinloader": "CustomSkinLoader",
  "fastbench": "FastWorkbench",
  "actuallyadditions": "Actually Additions",
  "baubles": "Baubles",
  "actuallybaubles": "Actually Baubles",
  "opencomputers": "OpenComputers",
  "actuallycomputers": "ActuallyComputers",
  "forgeendertech": "Forge Endertech",
  "adlods": "Large Ore Deposits",
  "advancedmortars": "Advanced Mortars",
  "redstoneflux": "Redstone Flux",
  "cofhcore": "CoFH Core",
  "libvulpes": "Vulpes library",
  "advancedrocketry": "Advanced Rocketry",
  "embers": "Embers Rekindled",
  "aetherworks": "AetherWorks",
  "crafttweaker": "CraftTweaker2",
  "endertweaker": "EnderTweaker",
  "mtlib": "MTLib",
  "modtweaker": "Mod Tweaker",
  "jei": "Just Enough Items",
  "art": "Advanced Rocketry Tweaker",
  "ctm": "CTM",
  "appliedenergistics2": "Applied Energistics 2",
  "codechickenlib": "CodeChicken Lib",
  "brandonscore": "Brandon's Core",
  "aenetvistool": "AE Net Vis Tool",
  "ae2fc": "AE2 Fluid Crafting",
  "bdlib": "BD Lib",
  "ae2stuff": "AE2 Stuff",
  "endercore": "EnderCore",
  "thaumcraft": "Thaumcraft",
  "cofhworld": "CoFH World",
  "thermalfoundation": "Thermal Foundation",
  "draconicevolution": "Draconic Evolution",
  "thermalexpansion": "Thermal Expansion",
  "enderio": "Ender IO",
  "mantle": "Mantle",
  "chisel": "Chisel",
  "enderiointegrationtic": "Ender IO Integration with Tinkers' Construct",
  "tinkersextras": "TinkersExtras",
  "tconstruct": "Tinkers' Construct",
  "p455w0rdslib": "p455w0rd's Library",
  "ae2wtlib": "AE2 Wireless Terminals (AE2WTLib)",
  "forgelin": "Shadowfacts' Forgelin",
  "mekanism": "Mekanism",
  "aeadditions": "AE Additions",
  "aetheriumashenarmor": "Aetherium Ashen Armor",
  "infinitylib": "InfinityLib",
  "agricraft": "AgriCraft",
  "aiimprovements": "AI Improvements",
  "aireducer": "AI Reducer",
  "akashictome": "Akashic Tome",
  "applecore": "AppleCore",
  "appleskin": "AppleSkin",
  "athenaeum": "Athenaeum",
  "craftingtweaks": "Crafting Tweaks",
  "mousetweaks": "Mouse Tweaks",
  "artisanworktables": "Artisan Worktables",
  "artisanautomation": "Artisan Automation",
  "botania_tweaks": "Botania Tweaks",
  "botania": "Botania",
  "bookshelf": "Bookshelf",
  "gamestages": "Game Stages",
  "patchouli": "Patchouli",
  "artisanintegrations": "Artisan Integrations",
  "artisanworkstumps": "Artisan Workstumps",
  "astralsorcery": "Astral Sorcery",
  "astral-level-nerf": "Astral Level Nerf",
  "attributefix": "Attribute Fix",
  "auracontrol": "AuraControl",
  "autoreglib": "AutoRegLib",
  "base": "B.A.S.E",
  "bedrockores": "Bedrock Ores",
  "bibliocraft": "BiblioCraft",
  "biometweaker": "BiomeTweaker",
  "biomesoplenty": "Biomes O' Plenty",
  "blockdrops": "Block Drops",
  "guideapi": "Guide-API",
  "bloodmagic": "Blood Magic: Alchemical Wizardry",
  "bloodarsenal": "Blood Arsenal",
  "bloodtinker": "Tinkering With Blood Magic",
  "bnbgaminglib": "BNBGamingLib",
  "bonsaitrees": "Bonsai Trees",
  "botanianeedsit": "Botania Needs These Things!",
  "buildinggadgets": "Building Gadgets",
  "chameleon": "Chameleon",
  "champions": "Champions",
  "chattweaks": "Chat Tweaks",
  "clienttweaks": "Client Tweaks",
  "clumps": "Clumps",
  "morpheus": "Morpheus",
  "comforts": "Comforts",
  "compactmachines3": "Compact Machines 3",
  "consolefilter": "Console Filter",
  "hdsutils": "HerodotusUtils",
  "contenttweaker": "ContentTweaker",
  "controlling": "Controlling",
  "cookingforblockheads": "Cooking for Blockheads",
  "corpsecomplex": "Corpse Complex",
  "cotro": "CoTRO",
  "ctgui": "CT-GUI",
  "crafttweakerjei": "CraftTweaker JEI Support",
  "crafttweakerutils": "CraftTweaker Utils",
  "ctintegration": "CraftTweaker Integration",
  "cucumber": "Cucumber Library",
  "cyclopscore": "Cyclops Core",
  "darkutils": "Dark Utilities",
  "journeymap": "JourneyMap",
  "defaultoptions": "Default Options",
  "diethopper": "Diet Hopper",
  "ding": "Ding",
  "discordcraft": "Minecraft Rich Presence",
  "dropt": "Dropt",
  "mcjtylib_ng": "McJtyLib",
  "efab": "EFab",
  "efabctbindings": "EFab CT Bindings",
  "elevatorid": "Elevator Mod",
  "emergingtechnology": "Emerging Technology",
  "enchdesc": "Enchantment Descriptions",
  "enderiobase": "Ender IO Base",
  "enderioconduits": "Ender IO Conduits",
  "enderioconduitsappliedenergistics": "Ender IO Applied Energistics Conduits",
  "enderioconduitsopencomputers": "Ender IO Open Computers Conduits",
  "enderioconduitsrefinedstorage": "Ender IO Refined Storage Conduits",
  "enderiointegrationforestry": "Ender IO Integration with Forestry",
  "enderiointegrationticlate": "Ender IO Integration with Tinkers' Construct",
  "enderioinvpanel": "Ender IO Inventory Panel",
  "ftblib": "FTB Library",
  "enderiomachines": "Ender IO Machines",
  "enderiopowertools": "Ender IO Powertools",
  "enderiofluxified": "EnderIO Fluxified",
  "enderstorage": "EnderStorage",
  "entityculling": "Entity Culling",
  "satako": "Satako",
  "extended_item_information": "Extended Item Information",
  "extendedcrafting": "ExtendedCrafting: Nomifactory Edition",
  "factorytech": "Factory Tech",
  "findme": "FindMe",
  "konkrete": "Konkrete",
  "fancymenu": "FancyMenu",
  "fastfurnace": "FastFurnace",
  "fastleafdecay": "Fast Leaf Decay",
  "flopper": "Flopper",
  "libnine": "libnine",
  "storagedrawers": "Storage Drawers",
  "fluiddrawers": "Fluid Drawers",
  "fluxnetworks": "Flux Networks",
  "foamfix": "FoamFix",
  "ftbultimine": "FTB Ultimine",
  "ftbbackups": "FTB Backups",
  "ftbguides": "FTB Guides",
  "ftbutilities": "FTB Utilities",
  "itemfilters": "Item Filters",
  "ftbquests": "FTB Quests",
  "gravestone": "Gravestone Mod",
  "growthcraft": "Growthcraft",
  "growthcraft_fishtrap": "Growthcraft Fishtrap",
  "growthcraft_apples": "Growthcraft Apples",
  "growthcraft_cellar": "Growthcraft Cellar",
  "growthcraft_grapes": "Growthcraft Grapes",
  "growthcraft_bamboo": "Growthcraft Bamboo",
  "growthcraft_bees": "Growthcraft Bees",
  "growthcraft_rice": "Growthcraft Rice",
  "growthcraft_hops": "Growthcraft Hops",
  "growthcraft_milk": "Growthcraft Milk",
  "modularmachinery": "Modular Machinery",
  "pneumaticcraft": "PneumaticCraft: Repressurized",
  "gugu-utils": "GuGu Utils",
  "gunpowderlib": "GunpowderLib",
  "hammercore": "Hammer Core",
  "hungerinpeace": "Hunger In Peace",
  "ifoccompat": "Industrial Foregoing / OC Compat",
  "improvedbackpacks": "Improved Backpacks",
  "incorporeal": "Incorporeal",
  "teslacorelib": "Tesla Core Lib",
  "industrialforegoing": "Industrial Foregoing",
  "industrialrenewal": "Industrial Renewal",
  "infernalmobs": "Infernal Mobs",
  "initialinventory": "InitialInventory",
  "nuclearcraft": "NuclearCraft",
  "rftools": "RFTools",
  "integrationforegoing": "Integration Foregoing",
  "inventorytweaks": "Inventory Tweaks",
  "inworldcrafting": "InWorldCrafting",
  "ironchest": "Iron Chest",
  "ironjetpacks": "Iron Jetpacks",
  "itemstages": "Item Stages",
  "jeiexporter": "JEIExporter",
  "jeiintegration": "JEI Integration",
  "jetif": "Just Enough Throwing In Fluids",
  "jecalculation": "Just Enough Calculation",
  "justenoughdrags": "Just Enough Drags",
  "jee": "Just Enough Energistics",
  "jeid": "JustEnoughIDs",
  "loottweaker": "LootTweaker",
  "jeresources": "Just Enough Resources",
  "kleeslabs": "KleeSlabs",
  "letsencryptcraft": "Let's Encrypt Craft",
  "lttweaker": "Loot Table Tweaker",
  "magneticraft": "Magneticraft",
  "manatweaks": "ManaTweaks",
  "manavisualizer": "manavisualizer",
  "mekanismgenerators": "Mekanism: Generators",
  "mekanismtools": "Mekanism: Tools",
  "mobstages": "Mob Stages",
  "modelloader": "ModelLoader",
  "modularcontroller": "Modular Controller",
  "modularmagic": "Modular Magic",
  "naturescompass": "Nature's Compass",
  "neat": "Neat",
  "netherportalfix": "NetherPortalFix",
  "norecipebook": "No Recipe Book",
  "eioocshim": "EnderIO OpenComputer shim",
  "xnet": "XNet",
  "ocxnetdriver": "OpenComputers Xnet Driver",
  "packagedauto": "PackagedAuto",
  "packagedexcrafting": "PackagedExCrafting",
  "packmode": "PackMode",
  "packmodemenu": "PackModeMenu",
  "placebo": "Placebo",
  "teslathingies": "Tesla Powered Thingies",
  "prodigytech": "Prodigy Tech",
  "theoneprobe": "The One Probe",
  "pyrotech": "Pyrotech",
  "qmd": "Quantum Minecraft Dynamics",
  "randomportals": "RandomPortals",
  "randomtweaks": "RandomTweaks",
  "requious": "Requious Frakto",
  "resourceloader": "Resource Loader",
  "rftoolscontrol": "RFTools Control",
  "rftoolspower": "RFToolsPower",
  "rftpwroc": "RFTools Power / OC Integration",
  "rockytweaks": "@NAME@",
  "roughmobsrevamped": "Rough Mobs Revamped",
  "ruins": "Ruins Mod",
  "silentlib": "Silent Lib",
  "scalinghealth": "Scaling Health",
  "storagenetwork": "Simple Storage Network",
  "simple_trophies": "Simple Trophies",
  "smooth-scrolling-everywhere": "Smooth Scrolling Everywhere",
  "snad": "Snad",
  "soot": "Soot",
  "specialmobs": "Special Mobs",
  "srparasites": "Scape and Run Parasites",
  "stg": "SwingThroughGrass",
  "storagedrawersextra": "Storage Drawers Extras",
  "surge": "Surge",
  "tc6aspects4jei": "TC6 Aspects for JEI",
  "tconevo": "Tinkers' Evolution",
  "tellme": "Tell Me",
  "tcresearchpatcher": "Thaumcraft Research Patcher",
  "thaumadditions": "Thaumic Additions: Reconstructed",
  "thaumicaugmentation": "Thaumic Augmentation",
  "thaumcomp": "Thaumic Computers",
  "thaumicjei": "ThaumicJEI",
  "thaumicenergistics": "Thaumic Energistics",
  "tcinventoryscan": "Thaumcrafft Inventory Scanning",
  "thaumicperiphery": "Thaumic Periphery",
  "thaumicspeedup": "Thaumic Speedup",
  "thaumicterminal": "Thaumic Terminal",
  "thaumictinkerer": "Thaumic Tinkerer",
  "thaumicwonders": "Thaumic Wonders",
  "thermalcultivation": "Thermal Cultivation",
  "thermaldynamics": "Thermal Dynamics",
  "thermalinnovation": "Thermal Innovation",
  "thermaltinkering": "Thermal Tinkering",
  "tinker_io": "Tinker I/O",
  "tinkersjei": "Tinker's JEI",
  "tinkersoc": "Tinkers Construct OpenComputers Driver",
  "tinkersoredictcache": "TinkersOreDictCache",
  "tips": "Tips",
  "tipthescales": "TipTheScales",
  "toastcontrol": "Toast Control",
  "topaddons": "TOP Addons",
  "topography": "Topography",
  "torchmaster": "TorchMaster",
  "unloader": "Unloader",
  "versioner": "Versioner",
  "wanionlib": "WanionLib",
  "waystones": "Waystones",
  "wct": "Wireless Crafting Terminal 2",
  "wft": "Wireless Fluid Terminal",
  "wit": "Wireless Interface Terminal",
  "wpt": "Wireless Pattern Terminal",
  "wgblockreplacer": "WorldGen Block Replacer",
  "xlfoodmod": "XL Food Mod",
  "recipehandler": "Yet Another Recipe Conflict Fixer",
  "ynot": "YNot",
  "zenutils": "ZenUtils",
  "phosphor-lighting": "Phosphor Lighting Engine",
  "reauth": "ReAuth",
  "ocsensors": "OpenComputers Sensors",
  "teslacorelib_registries": "Tesla Core Lib Registries",
  "tweakersconstructpostload": "Tweakers Construct Post Load",
  "unidict": "UniDict",
  "bansoukou": "Bansoukou",
  "ic2patcher-core": "IC2 Patcher Core",
  "creativecoredummy": "CreativeCoreDummy",
  "ivtoolkit": "IvToolkit",
  "littletilescore": "LittleTilesCore",
  "openmodscore": "OpenModsLib Core",
  "bnbgamingcore": "BnBGamingCore",
  "tickcentral": "TickCentral",
  "ic2": "IndustrialCraft 2",
  "forestry": "Forestry",
  "craftstudioapi": "CraftStudio API",
  "harvestcraft": "Pam's HarvestCraft",
  "toolprogression": "Tool Progression",
  "twilightforest": "The Twilight Forest",
  "animania": "Animania",
  "betteranimals": "Cyber's Better Animal Models",
  "quark": "Quark: RotN Edition",
  "exnihilocreatio": "Ex Nihilo Creatio",
  "excompressum": "Ex Compressum",
  "additionalcompression": "Additional Compression",
  "engineersdecor": "Engineer's Decor",
  "immersiveengineering": "Immersive Engineering",
  "waila": "Waila",
  "computercraft": "CC: Tweaked",
  "cyclicmagic": "Cyclic",
  "alfinivia": "Alfinivia",
  "angermanagement": "Anger Management",
  "animus": "Animus",
  "aquaacrobatics": "Aqua Acrobatics",
  "architecturecraft": "ArchitectureCraft",
  "armorcurve": "Armor Curve",
  "armoreablemobs": "ArmoreableMobs",
  "conarm": "Construct's Armory",
  "armoryexpansion": "Armory Expansion",
  "armoryexpansion-custommaterials": "Armory Expansion - Custom Materials",
  "llibrary": "LLibrary",
  "iceandfire": "Ice and Fire",
  "armoryexpansion-iceandfire": "Armory Expansion - Ice and Fire",
  "armoryexpansion-matteroverdrive": "Armory Expansion - MatterOverdrive",
  "atlaslib": "Atlas Lib",
  "morphtool": "Morph-o-Tool",
  "avaritia": "Avaritia",
  "avaritiafurnace": "Avaritia Furnace",
  "avaritiaio": "Avaritia IO",
  "bhc": "Baubley Heart Canisters",
  "betteradvancements": "Better Advancements",
  "betterbiomeblend": "Better Biome Blend",
  "betterbuilderswands": "Better Builder's Wands",
  "bettercaves": "YUNG's Better Caves",
  "betterhurttimer": "Better Hurt Timer",
  "bettermineshafts": "YUNG's Better Mineshafts",
  "betterp2p": "Better P2P",
  "bilingualname": "bilingual Name",
  "biomeborderviewer": "Biome Border Viewer",
  "bloodsmeltery": "Blood Smeltery: A TCon Addon for Blood Magic",
  "bookdisplay": "Book Display",
  "bmtr": "Bring me the rings!",
  "brokenwings": "Broken Wings",
  "carryon": "Carry On",
  "cctweaked": "CC: Tweaked",
  "chunkpregenerator": "Chunk Pregenerator",
  "chunkanimator": "Chunk Animator",
  "claybucket": "Clay Bucket",
  "mysticalagriculture": "Mystical Agriculture",
  "mysticalagradditions": "Mystical Agradditions",
  "clochepp": "Cloche++",
  "collective": "Collective",
  "commoncapabilities": "CommonCapabilities",
  "colossalchests": "Colossal Chests",
  "colytra": "Colytra",
  "compactsolars": "Compact Solar Arrays",
  "conditionoverload": "Condition: Overload",
  "cosmeticarmorreworked": "CosmeticArmorReworked",
  "creativecore": "CreativeCore",
  "cryingghasts": "Crying Ghasts",
  "culinaryconstruct": "Culinary Construct",
  "custombackgrounds": "Custom Backgrounds",
  "custommainmenu": "Custom Main Menu",
  "damagetilt": "Damage Tilt",
  "deepmoblearning": "Deep Mob Learning",
  "deepmoblearningbm": "Deep Mob Learning - Blood Magic Addon",
  "defaultworldgenerator-port": "Default World Generator",
  "demagnetize": "Demagnetize",
  "discordsuite": "DiscordSuite",
  "dwmh": "Dude! Where's my Horse?",
  "dynamistics": "Dynamistics",
  "emberroot": "EmberRoot Zoo",
  "enablecheats": "Enable Cheats",
  "gasconduits": "GasConduits",
  "enderioendergy": "Ender IO endergy",
  "endreborn": "End: Reborn",
  "engineersdoors": "Engineer's Doors",
  "renderlib": "RenderLib",
  "entity_desync_fix": "EntityDesyncFix",
  "valkyrielib": "Valkyrie Lib",
  "environmentalmaterials": "Environmental Materials",
  "environmentaltech": "Environmental Tech",
  "extrautils2": "Extra Utilities 2",
  "zerocore": "Zero CORE",
  "bigreactors": "Extreme Reactors",
  "eyeofdragons": "Eye of Dragons",
  "fantasticlib": "Fantastic Lib",
  "farmingforblockheads": "Farming for Blockheads",
  "fencejumper": "Fence Jumper",
  "floralchemy": "Floralchemy",
  "fluidlogged_api": "Fluidlogged API",
  "sonarcore": "SonarCore",
  "fpsreducer": "FPS Reducer",
  "framedcompactdrawers": "Framed Compacting Drawers",
  "gamblingstyle": "Gambling Style",
  "gendustry": "GenDustry",
  "gendustryjei": "Gendustry JEI Addon",
  "advgenerators": "Advanced Generators",
  "givemebackmyhp": "Give me back my HP!",
  "grid": "Grid",
  "handoveryouritems": "Hand Over Your Items",
  "hbm": "Harder Branch Mining",
  "hole_filler_mod": "Hole Filler Mod",
  "horsestandstill": "Stupid Horse Stand Still",
  "horsetweaks": "Horse Tweaks",
  "ic2cropplugin": "IC2CropPlugin",
  "ic2patcher": "IC2 Patcher",
  "iconexporter": "IconExporter",
  "immersivecables": "Immersive Cables",
  "immersivepetroleum": "Immersive Petroleum",
  "incontrol": "InControl",
  "integrateddynamics": "Integrated Dynamics",
  "integratedcrafting": "Integrated Crafting",
  "integrateddynamicscompat": "IntegratedDynamics-Compat",
  "integratednbt": "Integrated NBT",
  "integratedterminals": "Integrated Terminals",
  "integratedterminalscompat": "IntegratedTerminals-Compat",
  "integratedtunnels": "Integrated Tunnels",
  "integratedtunnelscompat": "IntegratedTunnels-Compat",
  "randomthings": "Random Things",
  "rustic": "Rustic",
  "jaopcacustom": "Just A Ore Processing Compatibility Attempt: Customized",
  "jaopca": "JAOPCA",
  "oredictinit": "OreDictInit",
  "jeibees": "JEI Bees",
  "jepb": "Just Enough Pattern Banners",
  "jehc": "Just Enough HarvestCraft",
  "justenoughpetroleum": "Just Enough Petroleum",
  "justenoughreactors": "Just Enough Reactors",
  "keywizard": "Keyboard Wizard",
  "kirosblocks": "Kiro's Basic Blocks",
  "laggoggles": "LagGoggles",
  "threng": "Lazy AE2",
  "letmesleep": "Let Me Sleep",
  "littletiles": "LittleTiles",
  "spark": "spark",
  "loliasm": "LoliASM",
  "lootcapacitortooltips": "Loot Capacitor Tooltips",
  "lootr": "Lootr",
  "lunatriuscore": "LunatriusCore",
  "matc": "Mystical Agriculture Tiered Crystals",
  "materialchanger": "Material Changer",
  "immersivetech": "Immersive Technology",
  "mctsmelteryio": "Smeltery IO",
  "mechanics": "Mechanics",
  "mekatweaker": "MekaTweaker",
  "mia": "Minor Integrations and Additions",
  "minemenu": "MineMenu",
  "mineraltracker": "Mineral Tracker",
  "miningspeed2": "Precision Mining",
  "testdummy": "MmmMmmMmmMmm",
  "modularassembly": "Modular Assembly",
  "moredefaultoptions": "MoreDefaultOptions",
  "moreoverlays": "MoreOverlays",
  "mysticalcreations": "Mystical Creations",
  "reactorbuilder": "Reactor Builder",
  "psi": "Psi",
  "plustic": "PlusTiC",
  "wawla": "What Are We Looking At",
  "netherendingores": "Netherending Ores",
  "netherportalspread": "Nether Portal Spread",
  "noadvancements": "No Advancements",
  "neenergistics": "NotEnoughEnergistics",
  "notenoughrtgs": "Not Enough RTGs",
  "nutrition": "Nutrition",
  "oauth": "OAuth",
  "oreexcavation": "OreExcavation",
  "oeintegration": "OreExcavation Integration",
  "oldjava": "Old Java Warning",
  "openmods": "OpenModsLib",
  "openblocks": "OpenBlocks",
  "overpoweredarmorbar": "Overloaded Armor Bar",
  "particleculling": "Particle Culling",
  "ping": "Ping",
  "planefix": "PlaneFix",
  "plethora-core": "Plethora Core",
  "plethora": "Plethora",
  "plustweaks": "PlusTweaks",
  "pointer": "Pointer",
  "portabledrill": "Portable Drill",
  "potioncore": "Potion Core",
  "potiondescriptions": "Potion Descriptions",
  "prettybeaches": "Pretty Beaches",
  "projectintelligence": "Project Intelligence",
  "psicaster": "PSICaster",
  "psicosts": "Psio",
  "quarkoddities": "Quark Oddities",
  "quickleafdecay": "Quick Leaf Decay",
  "rats": "Rats",
  "reccomplex": "Recurrent Complex",
  "redstonearsenal": "Redstone Arsenal",
  "redstonerepository": "Redstone Repository",
  "rftdimtweak": "RFTools Dimensions Tweaker",
  "rftoolsdim": "RFTools Dimensions",
  "rttweaker": "Random Things Tweaker",
  "scalingfeast": "Scaling Feast",
  "scalingguis": "ScalingGUIs",
  "scannable": "Scannable",
  "schematica": "Schematica",
  "servertabinfo": "Server Tab Info",
  "simplelogin": "SimpleLogin",
  "smallernetherportals": "Smaller Nether Portals",
  "soundphysics": "Sound Physics",
  "spectral_edge": "Spectral Edge",
  "sqpatch": "Squeezer Patch",
  "supersoundmuffler": "Super Sound Muffler: Revived",
  "tconmodmod": "Tinkers' Modifier Modifier",
  "terracart": "TerraCart Reloaded",
  "thaumtweaks": "ThaumTweaks",
  "thermallogistics": "Thermal Logistics",
  "tinkersaddons": "Tinkers' Addons",
  "tcomplement": "Tinkers' Complement",
  "tinkertoolleveling": "Tinkers Tool Leveling",
  "tmel": "Too Many Efficiency Losses",
  "tombmanygraves": "Tomb Many Graves",
  "torohealthmod": "ToroHealth Damage Indicators",
  "toughnessbar": "Toughness bar",
  "travelersbackpack": "Traveler's Backpack",
  "treetweaker": "TreeTweaker",
  "triumph": "Triumph",
  "ts2k16": "Twerk-Sim 2K16",
  "tweakedpetroleum": "Tweaked Petroleum",
  "tweakedpetroleumgas": "Tweaked Petroleum: Gas Addon",
  "uteamcore": "U Team Core",
  "uberconduitprobe": "Uber Conduit Probe",
  "usefulrailroads": "Useful Railroads",
  "universalmodifiers": "Universal Modifiers",
  "vaultopic": "Vaultopic",
  "villagenames": "ยง6Village Names",
  "villagermarket": "Villager Market",
  "voidislandcontrol": "Void Island Control",
  "wailaharvestability": "Waila Harvestability",
  "xtones": "Xtones",
  "ydt": "You Dropped This",
  "zentoolforge": "Zen Toolforge",
  "danknull": "/dank/null",
  "betteranimalsplus": "Better Animals Plus",
  "rf-capability-adapter": "Capability Adapter",
  "industrialwires": "Industrial Wires",
  "jade": "Jade",
  "nimble": "Nimble",
  "solcarrot": "Spice of Life: Carrot Edition",
  "armoryexpansion-conarm": "Armory Expansion - Construct's Armory",
  "wrapup": "WrapUp"
}